[{"created":"2023-06-29 10:02.02","username":"alex","email":"alex@duck.com","phone":"(709)685-3999","token":"1igmcx9","expires":"2023-06-30T12:32:01.200Z","confirmed":true},{"created":"2023-06-29 10:06.48","username":"alex","email":"alex@duck.com","phone":"(709)685-3999","token":"yna4je","expires":"2023-06-30T12:36:28.800Z","confirmed":true},{"created":"2023-06-29 10:06.52","username":"alex","email":"alex@duck.com","phone":"(709)685-3999","token":"1ef77jx","expires":"2023-06-30T12:36:31.200Z","confirmed":true}]